{
  "autounattend": "answer_files/Windows10_ltsb/autounattend.xml",
  "cpu_num": "2",
  "disk_size": "61440",
  "disk_type_id": "1",
  "headless": "true",
  "memory": "2048",
  "iso_checksum": "sha256:69EFAC1DF9EC8066341D8C9B62297DDECE0E6B805533FDB6DD66BC8034FBA27A",
  "iso_url": "./iso/Windows10_21H2/19044.1288.211006-0501.21h2_release_svc_refresh_CLIENTENTERPRISEEVAL_OEMRET_x64FRE_en-us.iso",
  "hyperv_switchname": "packer-external",
  "switchname": "br0",
  "http_directory": "./src",
  "winrm_timeout": "1h",
  "vm_name": "Windows10_packer",
  "winrm_use_ntlm": "true",
  "winrm_use_ssl": "true",
  "winrm_insecure": "true",
  "output_directory": "D:\\Hyperv\\packer\\windows10_21h2",
  "nix_output_directory": " /home/libvirt/images/pool/",
  "win_temp_dir": "c:\\temp",
  "seven_zip_uri": "https://www.7-zip.org/a/7z2107-x64.exe",
  "seven_zip_installer": "7z2107-x64.exe",
  "chrome_installer": "GoogleChromeEnterpriseBundle64.zip",
  "keep_registered": "false",
  "python_uri": "https://www.python.org/ftp/python/2.7.18/python-2.7.18.amd64.msi",
  "vscode_installer": "VSCodeSetup-x64-1.67.0.exe",
  "git_uri":"https://github.com/git-for-windows/git/releases/download/v2.36.1.windows.1/Git-2.36.1-32-bit.exe",
  "git_installer": "Git-2.36.1-32-bit.exe",
  "ms_adk_uri":"https://go.microsoft.com/fwlink/?linkid=2120254",
  "ms_adk_installer":"adksetup.exe"
}